export_license/__init__.py
export_license/cli.py
export_license/exceptions.py
export_license/license_generator.py
export_license/license_manager.py
export_license/license_validator.py
export_license/setup.py
trump_pip/__init__.py
trump_pip/cli.py
trump_pip/language.py
trump_pip/tel.py
trump_pip/trump_simulator.py
trump_pip-11.4.5.dist-info/METADATA
trump_pip-11.4.5.dist-info/WHEEL
trump_pip-11.4.5.dist-info/entry_points.txt
trump_pip-11.4.5.dist-info/top_level.txt
trump_pip-11.4.5.dist-info/RECORD
